README.rst
setup.cfg
setup.py
emtex_common_utils/__init__.py
emtex_common_utils/manager.py
emtex_common_utils/middleware.py
emtex_common_utils/mixins.py
emtex_common_utils/models.py
emtex_common_utils/sqlalchemy_services.py
emtex_common_utils/utils.py
emtex_common_utils.egg-info/PKG-INFO
emtex_common_utils.egg-info/SOURCES.txt
emtex_common_utils.egg-info/dependency_links.txt
emtex_common_utils.egg-info/not-zip-safe
emtex_common_utils.egg-info/requires.txt
emtex_common_utils.egg-info/top_level.txt
emtex_common_utils/management/__init__.py
emtex_common_utils/management/commands/__init__.py
emtex_common_utils/management/commands/emtex_migrate.py